transpyle/__init__.py
transpyle/__main__.py
transpyle/_version.py
transpyle/configuration.py
transpyle/main.py
transpyle/py.typed
transpyle/c/__init__.py
transpyle/c/ast_generalizer.py
transpyle/c/parser.py
transpyle/cpp/__init__.py
transpyle/cpp/ast_generalizer.py
transpyle/cpp/compiler.py
transpyle/cpp/compiler_interface.py
transpyle/cpp/definitions.py
transpyle/cpp/parser.py
transpyle/cpp/unparser.py
transpyle/fortran/__init__.py
transpyle/fortran/ast_generalizer.py
transpyle/fortran/compiler.py
transpyle/fortran/compiler_interface.py
transpyle/fortran/definitions.py
transpyle/fortran/parser.py
transpyle/fortran/unparser.py
transpyle/general/__init__.py
transpyle/general/ast_generalizer.py
transpyle/general/auto_parser.py
transpyle/general/binder.py
transpyle/general/code_reader.py
transpyle/general/code_writer.py
transpyle/general/compiler.py
transpyle/general/compiler_interface.py
transpyle/general/exc.py
transpyle/general/language.py
transpyle/general/misc.py
transpyle/general/parser.py
transpyle/general/registry.py
transpyle/general/tools.py
transpyle/general/translator.py
transpyle/general/transpiler.py
transpyle/general/unparser.py
transpyle/pair/__init__.py
transpyle/pair/assertions.py
transpyle/pair/ast_annotations.py
transpyle/pair/ast_query.py
transpyle/pair/code_manipulation.py
transpyle/pair/inlining.py
transpyle/pair/loop_annotations.py
transpyle/pair/loop_unrolling.py
transpyle/pair/manipulate.py
transpyle/pair/synthetic_ast.py
transpyle/python/__init__.py
transpyle/python/parser.py
transpyle/python/translator.py
transpyle/python/unparser.py
transpyle/resources/c/README.md
transpyle/resources/c/_fake_defines.h
transpyle/resources/c/_fake_typedefs.h
transpyle/resources/c/stdbool.h
transpyle/resources/c/stdio.h
transpyle/resources/c/stdlib.h
transpyle/resources/c/string.h
transpyle/resources/cpp/README.md
transpyle/resources/cpp/numpy.i
transpyle-0.8.0.dist-info/LICENSE
transpyle-0.8.0.dist-info/METADATA
transpyle-0.8.0.dist-info/NOTICE
transpyle-0.8.0.dist-info/WHEEL
transpyle-0.8.0.dist-info/entry_points.txt
transpyle-0.8.0.dist-info/top_level.txt
transpyle-0.8.0.dist-info/RECORD
