Metadata-Version: 2.1
Name: transpyle
Version: 0.8.0
Summary: performance-oriented transpiler for Python
Home-page: https://github.com/mbdevpl/transpyle
Author: Mateusz Bysiek
Author-email: mateusz.bysiek@gmail.com
Maintainer: Mateusz Bysiek
Maintainer-email: mateusz.bysiek@gmail.com
License: Apache License 2.0
Keywords: compiler,just-in-time,source-to-source,transpilation,transpiler
Platform: UNKNOWN
Classifier: Development Status :: 2 - Pre-Alpha
Classifier: Environment :: Console
Classifier: Intended Audience :: Developers
Classifier: Intended Audience :: Science/Research
Classifier: License :: OSI Approved :: Apache Software License
Classifier: Natural Language :: English
Classifier: Operating System :: MacOS :: MacOS X
Classifier: Operating System :: POSIX :: Linux
Classifier: Programming Language :: Python :: 3.5
Classifier: Programming Language :: Python :: 3.6
Classifier: Programming Language :: Python :: 3.7
Classifier: Programming Language :: Python :: 3 :: Only
Classifier: Topic :: Education
Classifier: Topic :: Scientific/Engineering
Classifier: Topic :: Software Development :: Code Generators
Classifier: Topic :: Software Development :: Compilers
Classifier: Topic :: Software Development :: Pre-processors
Classifier: Topic :: Utilities
Requires-Python: >=3.5
Requires-Dist: argunparse
Requires-Dist: astunparse
Requires-Dist: colorama
Requires-Dist: colorlog
Requires-Dist: encrypted-config
Requires-Dist: horast (~=0.4.0)
Requires-Dist: pandas
Requires-Dist: setuptools (>=41.0)
Requires-Dist: static-typing (~=0.2.7)
Requires-Dist: typed-ast (~=1.4)
Requires-Dist: typed-astunparse (==2.*,>=2.1.4)
Requires-Dist: version-query (==1.*,>=1.0.5)
Provides-Extra: all
Requires-Dist: cython ; extra == 'all'
Requires-Dist: numpy ; extra == 'all'
Requires-Dist: open-fortran-parser (~=0.6.0) ; extra == 'all'
Requires-Dist: pcpp ; extra == 'all'
Requires-Dist: pycparser ; extra == 'all'
Requires-Dist: pyopencl ; extra == 'all'
Provides-Extra: c
Requires-Dist: cython ; extra == 'c'
Requires-Dist: pcpp ; extra == 'c'
Requires-Dist: pycparser ; extra == 'c'
Provides-Extra: cpp
Provides-Extra: cython
Requires-Dist: cython ; extra == 'cython'
Provides-Extra: fortran
Requires-Dist: numpy ; extra == 'fortran'
Requires-Dist: open-fortran-parser (~=0.6.0) ; extra == 'fortran'
Provides-Extra: opencl
Requires-Dist: pyopencl ; extra == 'opencl'
